{"id": "1170675521", "slug": "alice_vr", "title": "Alice VR", "developer": "Carbon Studio", "publisher": "Klabater", "gog_url": "https://www.gog.com/game/alice_vr", "image": "https://images.gog-statics.com/19a75d19f7bef65cc300e89a11b7061e2e9f13d8bbb2376a1a88f825a6ca6a1f.webp", "background": "4df223fddff861afee3cb1a2f8e0b517887457c092e15eb42bb0f4594f2e2b87", "rating": 2.6, "popularity_ranking": 4615, "release_timestamp": 1477515600, "genres": ["Adventure", "Narrative", "Puzzle"], "tags": ["Adventure", "Classic", "Exploration", "Indie", "Logic", "Mystery", "Narrative", "Puzzle", "Story Rich", "VR"], "is_indev": 0, "is_outdated": 0, "last_update": null, "current_version": "Patch 7", "gog_version": "Patch 7", "is_new": 0, "is_updated": 0, "is_mod": 0, "is_queued": 0, "is_uploading": 0, "infohash": null, "md5_filename": "alice_vr.md5", "md5_files": [{"hash": "9ea5215c356df9de0ed7a9ae3a011136", "filename": "Alice_VR_artbook_DE_ES_FR_PL_RU.zip"}, {"hash": "60c68b01391589ba34eb4a0b32b4e5dc", "filename": "Alice_VR_artbook_EN.zip"}, {"hash": "a5c378bf2ba8899ff39702f5c1386efe", "filename": "Alice_VR_developer_diaries.zip"}, {"hash": "be2c08847c23a13439bd7f874bba4452", "filename": "Alice_VR_soundtrack_FLAC.zip"}, {"hash": "9db242b0020622f8b21caf8b40b3a6ca", "filename": "Alice_VR_soundtrack_MP3.zip"}, {"hash": "0e3ea099395dc80aebf6b66185893846", "filename": "Alice_VR_wallpapers.zip"}, {"hash": "3c03aeb0dd2beaaaf9a848c87427d8ec", "filename": "setup_alice_vr_patch_7_(13019)-1.bin"}, {"hash": "5d741002a0942793d7f6ff5d342f686c", "filename": "setup_alice_vr_patch_7_(13019)-2.bin"}, {"hash": "1b5e333fa6d85ea7e35c612657df99bd", "filename": "setup_alice_vr_patch_7_(13019)-3.bin"}, {"hash": "438fcc06969358c8ef22fda6aff4678b", "filename": "setup_alice_vr_patch_7_(13019).exe"}], "magnet_link": null, "gogdb_url": "https://www.gogdb.org/product/1170675521", "pcgamingwiki_url": "https://pcgamingwiki.com/api/gog.php?page=1170675521", "download_links": {"goodie": {"fileq": {"id": "fileq", "name": "FileQ", "links": [{"label": "extras-alice.vr.rar", "link": "https://fileq.net/msomypbsgojn"}]}, "transferit": {"id": "transferit", "name": "Transfer.it", "links": [{"label": "extras-alice.vr.rar", "link": "https://transfer.it/t/dkPmNc9XkZJS"}]}, "gofile": {"id": "gofile", "name": "Gofile", "links": [{"label": "extras-alice.vr.rar", "link": "https://gofile.io/d/GnHVjt"}]}, "fileditch": {"id": "fileditch", "name": "FileDitch", "links": [{"label": "extras-alice.vr.rar", "link": "https://fileditchfiles.me/file.php?f=/alpha6/efa7e517bbb83110f37f/extras-alice.vr.rar"}]}, "1fichier": {"id": "1fichier", "name": "1fichier", "links": [{"label": "extras-alice.vr.rar", "link": "https://1fichier.com/?2knm6byti0mzgo2nrkdi"}]}}, "game": {"fileq": {"id": "fileq", "name": "FileQ", "links": [{"label": "game-alice.vr-(13019).rar", "link": "https://fileq.net/xl9phb2uoyof"}]}, "transferit": {"id": "transferit", "name": "Transfer.it", "links": [{"label": "game-alice.vr-(13019).rar", "link": "https://transfer.it/t/4UXqRJs3nZqK"}]}, "gofile": {"id": "gofile", "name": "Gofile", "links": [{"label": "game-alice.vr-(13019).rar", "link": "https://gofile.io/d/s0DVmB"}]}, "fileditch": {"id": "fileditch", "name": "FileDitch", "links": [{"label": "game-alice.vr-(13019).rar", "link": "https://fileditchfiles.me/file.php?f=/alpha6/e6deb49bec5c4ba6d470/game-alice.vr-%2813019%29.rar"}]}, "1fichier": {"id": "1fichier", "name": "1fichier", "links": [{"label": "game-alice.vr-(13019).rar", "link": "https://1fichier.com/?ip4cv0qr73xhwv7agif8"}]}}}, "files": {"game": [{"name": "setup_alice_vr_patch_7_(13019).exe", "type": "game", "size": "711.23 KB"}, {"name": "setup_alice_vr_patch_7_(13019)-1.bin", "type": "game", "size": "4 GB"}, {"name": "setup_alice_vr_patch_7_(13019)-2.bin", "type": "game", "size": "4 GB"}, {"name": "setup_alice_vr_patch_7_(13019)-3.bin", "type": "game", "size": "961 MB"}], "goodie": [{"name": "Alice_VR_artbook_DE_ES_FR_PL_RU.zip", "type": "goodie", "size": "342.05 MB"}, {"name": "Alice_VR_artbook_EN.zip", "type": "goodie", "size": "68.32 MB"}, {"name": "Alice_VR_developer_diaries.zip", "type": "goodie", "size": "224.75 MB"}, {"name": "Alice_VR_soundtrack_FLAC.zip", "type": "goodie", "size": "723.05 MB"}, {"name": "Alice_VR_soundtrack_MP3.zip", "type": "goodie", "size": "210.9 MB"}, {"name": "Alice_VR_wallpapers.zip", "type": "goodie", "size": "19.96 MB"}]}, "scraped_at": "2026-06-09T16:10:49.845Z"}