{"id": "1436955893", "slug": "archimedean_dynasty", "title": "Archimedean Dynasty", "developer": "Massive Development", "publisher": "Ubisoft", "gog_url": "https://www.gog.com/game/archimedean_dynasty", "image": "https://images.gog-statics.com/9934e957cf31b287b843ed8c4535bbf9a4ecbfcf8ccf37b332ddece8f30de78f.webp", "background": "ef6edb70f963707d65fe95a4f30b59907034aaa93e07871a0511a8433bf6678d", "rating": 4.6, "popularity_ranking": 4478, "release_timestamp": 846799200, "genres": ["Role-playing", "Sci-fi", "Simulation"], "tags": ["Classic", "Flight", "Role-playing", "Sci-fi", "Science", "Simulation", "Space"], "is_indev": 0, "is_outdated": 0, "last_update": null, "current_version": "1.120 (gog-4)", "gog_version": "1.120 (gog-4)", "is_new": 0, "is_updated": 0, "is_mod": 0, "is_queued": 0, "is_uploading": 0, "infohash": null, "md5_filename": "archimedean_dynasty.md5", "md5_files": [{"hash": "ee3f32ed0a73e8178b817297ff901294", "filename": "setup_archimedean_dynasty_2.0.0.4.exe"}], "magnet_link": null, "gogdb_url": "https://www.gogdb.org/product/1436955893", "pcgamingwiki_url": "https://pcgamingwiki.com/api/gog.php?page=1436955893", "download_links": {"game": {"gofile": {"id": "gofile", "name": "Gofile", "links": [{"label": "game-archimedean.dynasty-(2.0.0.4).rar", "link": "https://gofile.io/d/PTvbU0"}]}, "pixeldrain": {"id": "pixeldrain", "name": "Pixeldrain", "links": [{"label": "game-archimedean.dynasty-(2.0.0.4).rar", "link": "https://pixeldrain.com/u/pZ9XDSTd"}]}, "1fichier": {"id": "1fichier", "name": "1fichier", "links": [{"label": "game-archimedean.dynasty-(2.0.0.4).rar", "link": "https://1fichier.com/?4u4vqwpfd3ys4r4l4fnd"}]}}}, "files": {"game": [{"name": "setup_archimedean_dynasty_2.0.0.4.exe", "type": "game", "size": "977.86 MB"}]}, "scraped_at": "2026-06-09T16:03:18.393Z"}