{"id": "1879726525", "slug": "base_one", "title": "Base One", "developer": "Pixfroze", "publisher": "Blowfish Studios", "gog_url": "https://www.gog.com/game/base_one", "image": "https://images.gog-statics.com/88b14989964235eb2cb31a7dc8b8df3a4ed777d686ed8236d516465e5f7f920b.webp", "background": "1cb6b32c3b08857377923e90b93c8f1fb477461e7506eed6895c3f9b757d0258", "rating": 2.4, "popularity_ranking": 5956, "release_timestamp": 1620680400, "genres": ["Sci-fi", "Simulation", "Strategy"], "tags": ["Crafting", "Exploration", "Isometric", "Management", "Military", "Real-Time", "Sci-fi", "Science", "Simulation", "Space", "Strategy", "Survival"], "is_indev": 0, "is_outdated": 0, "last_update": "2022-02-12T22:05:08.000000Z", "current_version": "release_1.4.0.8_e41965c41", "gog_version": "release_1.4.0.8_e41965c41", "is_new": 0, "is_updated": 0, "is_mod": 0, "is_queued": 0, "is_uploading": 0, "infohash": null, "md5_filename": "base_one.md5", "md5_files": [{"hash": "8869cea679b65978e47ffb90604d3d50", "filename": "setup_baseone_release_1.4.0.8_e41965c41_(53424)-1.bin"}, {"hash": "12e42f1cc9e0c76b0ec834af2ff33de1", "filename": "setup_baseone_release_1.4.0.8_e41965c41_(53424)-2.bin"}, {"hash": "a5d52933804314cbf36986f2235d7aa5", "filename": "setup_baseone_release_1.4.0.8_e41965c41_(53424).exe"}], "magnet_link": null, "gogdb_url": "https://www.gogdb.org/product/1879726525", "pcgamingwiki_url": "https://pcgamingwiki.com/api/gog.php?page=1879726525", "download_links": {"game": {"gofile": {"id": "gofile", "name": "Gofile", "links": [{"label": "game-base.one-(53424).rar", "link": "https://gofile.io/d/u45mN1"}]}, "pixeldrain": {"id": "pixeldrain", "name": "Pixeldrain", "links": [{"label": "game-base.one-(53424).rar", "link": "https://pixeldrain.com/u/bqsbX4GZ"}]}, "1fichier": {"id": "1fichier", "name": "1fichier", "links": [{"label": "game-base.one-(53424).rar", "link": "https://1fichier.com/?6v9ry1hye7t3yxm3f2y8"}]}}}, "files": {"game": [{"name": "setup_baseone_release_1.4.0.8_e41965c41_(53424).exe", "type": "game", "size": "878.69 KB"}, {"name": "setup_baseone_release_1.4.0.8_e41965c41_(53424)-1.bin", "type": "game", "size": "4 GB"}, {"name": "setup_baseone_release_1.4.0.8_e41965c41_(53424)-2.bin", "type": "game", "size": "1.8 GB"}]}, "scraped_at": "2026-06-09T15:57:52.116Z"}