{"id": "1207664573", "slug": "bionic_dues", "title": "Bionic Dues", "developer": "Arcen Games", "publisher": "Arcen Games", "gog_url": "https://www.gog.com/game/bionic_dues", "image": "https://images.gog-statics.com/e267b7ea656ef09b9d35ed4a31c6eea93913a32b9af93f96e9e101f3d4ae29ce.webp", "background": "bda96c5947acf25732032efd22dc93b48d30a2f6e9302773d8058360cac39e02", "rating": 3.9, "popularity_ranking": 5610, "release_timestamp": 1381179600, "genres": ["Roguelike", "Strategy", "Turn-based"], "tags": ["2D", "Classic", "Cyberpunk", "Great Soundtrack", "Indie", "Post-apocalyptic", "Procedural Generation", "Robots", "Roguelike", "Roguelite", "Science", "Strategy", "Tactical", "Top-Down", "Turn-Based"], "is_indev": 0, "is_outdated": 0, "last_update": null, "current_version": "1.007", "gog_version": "1.007", "is_new": 0, "is_updated": 0, "is_mod": 0, "is_queued": 0, "is_uploading": 0, "infohash": null, "md5_filename": "bionic_dues.md5", "md5_files": [{"hash": "9e9fe739e65ec731e252d55d4dc77bfc", "filename": "bionic_dues_artworks.zip"}, {"hash": "5de8561a8760a21c18630e3f50b28df4", "filename": "bionic_dues_avatars.zip"}, {"hash": "df1d6152d57ad035ef90d4c6f6fca5ed", "filename": "bionic_dues_comic.zip"}, {"hash": "85a69b2ef7ba1221896ef58c5ea033b2", "filename": "bionic_dues_sketches.zip"}, {"hash": "df7b3e66f0baa4ddacddac06a331df25", "filename": "bionic_dues_wallpaper.zip"}, {"hash": "69512c27a03789ac7df430318754476a", "filename": "setup_bionic_dues_1.007_(20674).exe"}], "magnet_link": null, "gogdb_url": "https://www.gogdb.org/product/1207664573", "pcgamingwiki_url": "https://pcgamingwiki.com/api/gog.php?page=1207664573", "download_links": {"goodie": {"gofile": {"id": "gofile", "name": "Gofile", "links": [{"label": "extras-bionic.dues.rar", "link": "https://gofile.io/d/LNrjCw"}]}, "fileditch": {"id": "fileditch", "name": "FileDitch", "links": [{"label": "extras-bionic.dues.rar", "link": "https://small.fileditchstuff.me/s15/BFtWplMjUMxwcHAhNfVN.rar"}]}, "pixeldrain": {"id": "pixeldrain", "name": "Pixeldrain", "links": [{"label": "extras-bionic.dues.rar", "link": "https://pixeldrain.com/u/PFq3BFwX"}]}, "1fichier": {"id": "1fichier", "name": "1fichier", "links": [{"label": "extras-bionic.dues.rar", "link": "https://1fichier.com/?tipzgv1ovygn8bpalqfk"}]}}, "game": {"gofile": {"id": "gofile", "name": "Gofile", "links": [{"label": "game-bionic.dues-(20674).rar", "link": "https://gofile.io/d/0xYXgy"}]}, "fileditch": {"id": "fileditch", "name": "FileDitch", "links": [{"label": "game-bionic.dues-(20674).rar", "link": "https://small.fileditchstuff.me/s15/PpPkVnhEleNFbXxvtDa.rar"}]}, "pixeldrain": {"id": "pixeldrain", "name": "Pixeldrain", "links": [{"label": "game-bionic.dues-(20674).rar", "link": "https://pixeldrain.com/u/Hx3oWsij"}]}, "1fichier": {"id": "1fichier", "name": "1fichier", "links": [{"label": "game-bionic.dues-(20674).rar", "link": "https://1fichier.com/?9f8v1i9w0sldr14pflmg"}]}}}, "files": {"game": [{"name": "setup_bionic_dues_1.007_(20674).exe", "type": "game", "size": "214.69 MB"}], "goodie": [{"name": "bionic_dues_artworks.zip", "type": "goodie", "size": "7.91 MB"}, {"name": "bionic_dues_avatars.zip", "type": "goodie", "size": "233.15 KB"}, {"name": "bionic_dues_comic.zip", "type": "goodie", "size": "50.2 MB"}, {"name": "bionic_dues_sketches.zip", "type": "goodie", "size": "15.01 MB"}, {"name": "bionic_dues_wallpaper.zip", "type": "goodie", "size": "638.72 KB"}]}, "scraped_at": "2026-06-09T15:55:35.380Z"}