{"id": "1786008709", "slug": "chains_of_fury", "title": "Chains of Fury", "developer": "Cobble Games", "publisher": "Fulqrum Publishing", "gog_url": "https://www.gog.com/game/chains_of_fury", "image": "https://images.gog-statics.com/ca9135a1d525bf538ede9615e0e6962c4b391a722ba05cf1aa8e5e3cd946f480.webp", "background": "dd3f1a86fe6527a591eb7806c57fc6c0172ef933e3a13bb30159a0db0ccf5735", "rating": 1.6, "popularity_ranking": 4295, "release_timestamp": 1726434000, "genres": ["Action", "Metroidvania", "Shooter"], "tags": ["Action", "Dark Comedy", "FPS", "First-Person", "Indie", "Metroidvania", "Multiplayer", "Retro", "Shooter"], "is_indev": 0, "is_outdated": 0, "last_update": "2024-11-11T05:23:27.000000Z", "current_version": "1.0.1.6", "gog_version": "1.0.1.6", "is_new": 0, "is_updated": 0, "is_mod": 0, "is_queued": 0, "is_uploading": 0, "infohash": "4808ae98ef9ef131d2d6a8d2d739aeb71d313043", "md5_filename": "chains_of_fury.md5", "md5_files": [{"hash": "79b8f0c2213a892a8e8fa7b43b0ff3a8", "filename": "setup_chains_of_fury_1.0.1.6_(64bit)_(77391).exe"}], "magnet_link": "magnet:?xt=urn:btih:4808ae98ef9ef131d2d6a8d2d739aeb71d313043&dn=Chains%20of%20Fury&tr=udp%3A%2F%2Ftracker.opentrackr.org%3A1337%2Fannounce&tr=udp%3A%2F%2Fexodus.desync.com%3A6969%2Fannounce&tr=udp%3A%2F%2Fopen.stealth.si%3A80%2Fannounce&tr=udp%3A%2F%2Ftracker-udp.gbitt.info%3A80%2Fannounce", "gogdb_url": "https://www.gogdb.org/product/1786008709", "pcgamingwiki_url": "https://pcgamingwiki.com/api/gog.php?page=1786008709", "download_links": {"game": {"gofile": {"id": "gofile", "name": "Gofile", "links": [{"label": "game-chains.of.fury-(77391).rar", "link": "https://gofile.io/d/4btaIa"}]}, "pixeldrain": {"id": "pixeldrain", "name": "Pixeldrain", "links": [{"label": "game-chains.of.fury-(77391).rar", "link": "https://pixeldrain.com/u/aWdzGkHw"}]}, "1fichier": {"id": "1fichier", "name": "1fichier", "links": [{"label": "game-chains.of.fury-(77391).rar", "link": "https://1fichier.com/?vkpytxle3h9gc6162uic"}]}}}, "files": {"game": [{"name": "setup_chains_of_fury_1.0.1.6_(64bit)_(77391).exe", "type": "game", "size": "1.16 GB"}]}, "scraped_at": "2026-06-09T15:48:42.285Z"}