{"id": "1086307939", "slug": "deadlink", "title": "Deadlink", "developer": "Gruby Entertainment", "publisher": "SuperGG.com", "gog_url": "https://www.gog.com/game/deadlink", "image": "https://images.gog-statics.com/00eb99770bbb94a8e93ee0df24cb439b61b64f2f768d6a95652606fcdf6761d9.webp", "background": "2357bb158719fcc7e276331a0f89c6d1b0b05270c151a58d1648389d74c22b9a", "rating": 4.7, "popularity_ranking": 879, "release_timestamp": 1690405200, "genres": ["Action", "FPP", "Roguelike"], "tags": ["Action", "Cartoony", "Cyberpunk", "Difficult", "FPS", "First-Person", "Perma Death", "Post-apocalyptic", "Roguelike", "Roguelite", "Sci-fi"], "is_indev": 0, "is_outdated": 0, "last_update": "2025-10-07T14:30:15.000000Z", "current_version": "1.2.32484", "gog_version": "1.2.32484", "is_new": 0, "is_updated": 0, "is_mod": 0, "is_queued": 0, "is_uploading": 0, "infohash": "cd626c79e5e9be561bdcdb003b8fb79f7d8cc436", "md5_filename": "deadlink.md5", "md5_files": [{"hash": "617e1b0ecc427d5689e61ae56fbc9a97", "filename": "deadlink_soundtrack_mp3.zip"}, {"hash": "53308341e79d2766e7c810c0529f9f41", "filename": "deadlink_soundtrack_wav.zip"}, {"hash": "2f316790189eeab7be02cdae2f374508", "filename": "setup_deadlink_1.2.32484_(64bit)_(85458)-1.bin"}, {"hash": "cf645cc06cad6387b3a26b5dbf4cc42e", "filename": "setup_deadlink_1.2.32484_(64bit)_(85458).exe"}], "magnet_link": "magnet:?xt=urn:btih:cd626c79e5e9be561bdcdb003b8fb79f7d8cc436&dn=Deadlink&tr=udp%3A%2F%2Ftracker.opentrackr.org%3A1337%2Fannounce&tr=udp%3A%2F%2Fexodus.desync.com%3A6969%2Fannounce&tr=udp%3A%2F%2Fopen.stealth.si%3A80%2Fannounce&tr=udp%3A%2F%2Ftracker-udp.gbitt.info%3A80%2Fannounce", "gogdb_url": "https://www.gogdb.org/product/1086307939", "pcgamingwiki_url": "https://pcgamingwiki.com/api/gog.php?page=1086307939", "download_links": {"goodie": {"fileq": {"id": "fileq", "name": "FileQ", "links": [{"label": "extras-deadlink.rar", "link": "https://fileq.net/vault/8bVPaOWyyf/goggames_-g49DEb_"}]}, "gofile": {"id": "gofile", "name": "Gofile", "links": [{"label": "extras-deadlink.rar", "link": "https://gofile.io/d/nnJMiC"}]}, "pixeldrain": {"id": "pixeldrain", "name": "Pixeldrain", "links": [{"label": "extras-deadlink.rar", "link": "https://pixeldrain.com/u/JmSg8CX5"}]}, "1fichier": {"id": "1fichier", "name": "1fichier", "links": [{"label": "extras-deadlink.rar", "link": "https://1fichier.com/?at33okl5h9qjqfcragwj"}]}}, "game": {"fileq": {"id": "fileq", "name": "FileQ", "links": [{"label": "game-deadlink-(85458).rar", "link": "https://fileq.net/vault/QQyxGhpa9I/goggames_-a6oA7A_"}]}, "gofile": {"id": "gofile", "name": "Gofile", "links": [{"label": "game-deadlink-(85458).rar", "link": "https://gofile.io/d/yhOfve"}]}, "pixeldrain": {"id": "pixeldrain", "name": "Pixeldrain", "links": [{"label": "game-deadlink-(85458).rar", "link": "https://pixeldrain.com/u/PeSSDsvG"}]}, "1fichier": {"id": "1fichier", "name": "1fichier", "links": [{"label": "game-deadlink-(85458).rar", "link": "https://1fichier.com/?wn8xzmyvwuw7wu19w94c"}]}}}, "files": {"game": [{"name": "setup_deadlink_1.2.32484_(64bit)_(85458).exe", "type": "game", "size": "871.68 KB"}, {"name": "setup_deadlink_1.2.32484_(64bit)_(85458)-1.bin", "type": "game", "size": "3.7 GB"}], "goodie": [{"name": "deadlink_soundtrack_mp3.zip", "type": "goodie", "size": "175.97 MB"}, {"name": "deadlink_soundtrack_wav.zip", "type": "goodie", "size": "1.13 GB"}]}, "scraped_at": "2026-06-09T15:39:39.315Z"}