{"id": "1121892325", "slug": "disney_the_jungle_book", "title": "Disney The Jungle Book", "developer": "Eurocom", "publisher": "Disney", "gog_url": "https://www.gog.com/game/disney_the_jungle_book", "image": "https://images.gog-statics.com/183ee4e2ca273869cc29bb543d97afb55f1a99e7ca0d03144f13672544bbaadb.webp", "background": "9ad0c31bba37bfc9f8c10c4d553715dd0cf013771e94721ab021bc1898a47ac6", "rating": 3.8, "popularity_ranking": 4411, "release_timestamp": 776898000, "genres": ["Action", "Arcade", "Platformer"], "tags": ["2D", "Action", "Arcade", "Platformer"], "is_indev": 0, "is_outdated": 0, "last_update": null, "current_version": "(gog-5)", "gog_version": "(gog-5)", "is_new": 0, "is_updated": 0, "is_mod": 0, "is_queued": 0, "is_uploading": 0, "infohash": null, "md5_filename": "disney_the_jungle_book.md5", "md5_files": [{"hash": "97860c96f2bf09adfcd6e914c80dfc17", "filename": "jungle_book_16-bit_poster_jpg.zip"}, {"hash": "1ca35aa0cc9f5564ecaf1d455d30091e", "filename": "setup_disneys_the_jungle_book_2.0.0.5.exe"}], "magnet_link": null, "gogdb_url": "https://www.gogdb.org/product/1121892325", "pcgamingwiki_url": "https://pcgamingwiki.com/api/gog.php?page=1121892325", "download_links": {"goodie": {"gofile": {"id": "gofile", "name": "Gofile", "links": [{"label": "extras-disney.the.jungle.book.rar", "link": "https://gofile.io/d/ngnmZi"}]}, "fileditch": {"id": "fileditch", "name": "FileDitch", "links": [{"label": "extras-disney.the.jungle.book.rar", "link": "https://fileditchfiles.me/file.php?f=/s22/xmtDDmsWugbcjMJeUtj.rar"}]}, "pixeldrain": {"id": "pixeldrain", "name": "Pixeldrain", "links": [{"label": "extras-disney.the.jungle.book.rar", "link": "https://pixeldrain.com/u/b2JLHCFz"}]}, "1fichier": {"id": "1fichier", "name": "1fichier", "links": [{"label": "extras-disney.the.jungle.book.rar", "link": "https://1fichier.com/?jln0ct6hddiafuouh689"}]}}, "game": {"gofile": {"id": "gofile", "name": "Gofile", "links": [{"label": "game-disney.the.jungle.book-(2.0.0.5).rar", "link": "https://gofile.io/d/BY8jxh"}]}, "pixeldrain": {"id": "pixeldrain", "name": "Pixeldrain", "links": [{"label": "game-disney.the.jungle.book-(2.0.0.5).rar", "link": "https://pixeldrain.com/u/mdVDn78c"}]}, "1fichier": {"id": "1fichier", "name": "1fichier", "links": [{"label": "game-disney.the.jungle.book-(2.0.0.5).rar", "link": "https://1fichier.com/?brw03raks6nmoxoq54bx"}]}}}, "files": {"game": [{"name": "setup_disneys_the_jungle_book_2.0.0.5.exe", "type": "game", "size": "18.11 MB"}], "goodie": [{"name": "jungle_book_16-bit_poster_jpg.zip", "type": "goodie", "size": "369.7 KB"}]}, "scraped_at": "2026-06-09T15:35:47.457Z"}