{"id": "1207658928", "slug": "dungeons_dragons_dragonshard", "title": "Dungeons & Dragons: Dragonshard", "developer": "Liquid Entertainment", "publisher": "Hasbro Inc.", "gog_url": "https://www.gog.com/game/dungeons_dragons_dragonshard", "image": "https://images.gog-statics.com/d00a3c552a6a13b8329fe40b00cad1a3b7f1a0d2203b6b68dde21dc8515e912d.webp", "background": "4887e64eec20e909a6a71b69a03c23891c17ef8814f50df1c082694cd8048162", "rating": 3.5, "popularity_ranking": 2346, "release_timestamp": 1127595600, "genres": ["Fantasy", "Role-playing", "Strategy"], "tags": ["Classic", "Fantasy", "Good Old Game", "Isometric", "Magic", "Management", "Only On GOG", "RTS", "Real-Time", "Role-playing", "Strategy", "Underground"], "is_indev": 0, "is_outdated": 0, "last_update": "2024-11-15T00:56:35.000000Z", "current_version": "1.02.0001", "gog_version": "1.02.0001", "is_new": 0, "is_updated": 0, "is_mod": 0, "is_queued": 0, "is_uploading": 0, "infohash": "a94f2f18c33c8befa7577f78f444105828fb1f2e", "md5_filename": "dungeons_dragons_dragonshard.md5", "md5_files": [{"hash": "751f920305a15e25a27efc49701d4a65", "filename": "Dragonshard_avatars.zip"}, {"hash": "7df4ed8fc9aba8a2dda5b09ca5f863b9", "filename": "Dragonshard_manual.zip"}, {"hash": "f689b54fb1fd5099b4e6e44de8b4769b", "filename": "Dragonshard_wallpapers.zip"}, {"hash": "daeed1bc903cc4bdf60336b1fabc6070", "filename": "setup_dungeons_and_dragons_-_dragonshard_1.02.0001_(15439)-1.bin"}, {"hash": "7f30ba047dfe4e8735231b8140284625", "filename": "setup_dungeons_and_dragons_-_dragonshard_1.02.0001_(15439).exe"}], "magnet_link": "magnet:?xt=urn:btih:a94f2f18c33c8befa7577f78f444105828fb1f2e&dn=Dungeons%20%26%20Dragons%3A%20Dragonshard&tr=udp%3A%2F%2Ftracker.opentrackr.org%3A1337%2Fannounce&tr=udp%3A%2F%2Fexodus.desync.com%3A6969%2Fannounce&tr=udp%3A%2F%2Fopen.stealth.si%3A80%2Fannounce&tr=udp%3A%2F%2Ftracker-udp.gbitt.info%3A80%2Fannounce", "gogdb_url": "https://www.gogdb.org/product/1207658928", "pcgamingwiki_url": "https://pcgamingwiki.com/api/gog.php?page=1207658928", "download_links": {"goodie": {"gofile": {"id": "gofile", "name": "Gofile", "links": [{"label": "extras-dungeons.dragons.dragonshard.rar", "link": "https://gofile.io/d/fiIBhf"}]}, "fileditch": {"id": "fileditch", "name": "FileDitch", "links": [{"label": "extras-dungeons.dragons.dragonshard.rar", "link": "https://small.fileditchstuff.me/s18/TKhLQDYmJTxBbtCQoKTM.rar"}]}, "pixeldrain": {"id": "pixeldrain", "name": "Pixeldrain", "links": [{"label": "extras-dungeons.dragons.dragonshard.rar", "link": "https://pixeldrain.com/u/3JVzntmf"}]}, "1fichier": {"id": "1fichier", "name": "1fichier", "links": [{"label": "extras-dungeons.dragons.dragonshard.rar", "link": "https://1fichier.com/?imjv1o1ygayx8gsg59ra"}]}}, "game": {"gofile": {"id": "gofile", "name": "Gofile", "links": [{"label": "game-dungeons.dragons.dragonshard-(15439).rar", "link": "https://gofile.io/d/nFvFe2"}]}, "pixeldrain": {"id": "pixeldrain", "name": "Pixeldrain", "links": [{"label": "game-dungeons.dragons.dragonshard-(15439).rar", "link": "https://pixeldrain.com/u/YvHhjS25"}]}, "1fichier": {"id": "1fichier", "name": "1fichier", "links": [{"label": "game-dungeons.dragons.dragonshard-(15439).rar", "link": "https://1fichier.com/?x87uqmd3audvgqdmtjqx"}]}}}, "files": {"game": [{"name": "setup_dungeons_and_dragons_-_dragonshard_1.02.0001_(15439).exe", "type": "game", "size": "810.55 KB"}, {"name": "setup_dungeons_and_dragons_-_dragonshard_1.02.0001_(15439)-1.bin", "type": "game", "size": "892.76 MB"}], "goodie": [{"name": "Dragonshard_avatars.zip", "type": "goodie", "size": "121.98 KB"}, {"name": "Dragonshard_manual.zip", "type": "goodie", "size": "2.45 MB"}, {"name": "Dragonshard_wallpapers.zip", "type": "goodie", "size": "23.14 MB"}]}, "scraped_at": "2026-06-09T15:32:23.606Z"}