{"id": "1980310428", "slug": "elements_and_build", "title": "Elements and Build", "developer": "ChuTouMiao Studio", "publisher": "2P Games", "gog_url": "https://www.gog.com/game/elements_and_build", "image": "https://images.gog-statics.com/b2d0489f2bbde768a02507eac4934e3026be5fff41b152f9c2251de96e976aeb.webp", "background": "e46ec9be8196cec2481e525aa4652bf570c6ec2f95d8f2fc409356fa1d374011", "rating": 3.2, "popularity_ranking": 1999, "release_timestamp": 1731362400, "genres": ["Building", "Roguelike", "Strategy"], "tags": ["2D", "Auto Battler", "Base Building", "Building", "Casual", "Deckbuilding", "Indie", "Roguelike", "Roguelite", "Strategy", "Tower Defense"], "is_indev": 0, "is_outdated": 0, "last_update": "2025-12-04T18:26:47.000000Z", "current_version": "1.0", "gog_version": "1.0", "is_new": 0, "is_updated": 0, "is_mod": 0, "is_queued": 0, "is_uploading": 0, "infohash": "b1059ad8a501ed0dcf2247641e4091e1ca303611", "md5_filename": "elements_and_build.md5", "md5_files": [{"hash": "0aadf90bc3b45d9ec8396634de76ec6a", "filename": "setup_elements_and_build_1.0_(86475).exe"}], "magnet_link": "magnet:?xt=urn:btih:b1059ad8a501ed0dcf2247641e4091e1ca303611&dn=Elements%20and%20Build&tr=udp%3A%2F%2Ftracker.opentrackr.org%3A1337%2Fannounce&tr=udp%3A%2F%2Fexodus.desync.com%3A6969%2Fannounce&tr=udp%3A%2F%2Fopen.stealth.si%3A80%2Fannounce&tr=udp%3A%2F%2Ftracker-udp.gbitt.info%3A80%2Fannounce", "gogdb_url": "https://www.gogdb.org/product/1980310428", "pcgamingwiki_url": "https://pcgamingwiki.com/api/gog.php?page=1980310428", "download_links": {"game": {"fileq": {"id": "fileq", "name": "FileQ", "links": [{"label": "game-elements.and.build-(86475).rar", "link": "https://fileq.net/vault/AQW4nJRm0r/goggames_-okbWGL_"}]}, "gofile": {"id": "gofile", "name": "Gofile", "links": [{"label": "game-elements.and.build-(86475).rar", "link": "https://gofile.io/d/rfYkc3"}]}, "pixeldrain": {"id": "pixeldrain", "name": "Pixeldrain", "links": [{"label": "game-elements.and.build-(86475).rar", "link": "https://pixeldrain.com/u/dPSiuiJM"}]}, "1fichier": {"id": "1fichier", "name": "1fichier", "links": [{"label": "game-elements.and.build-(86475).rar", "link": "https://1fichier.com/?u1kmy2kprxlz61ksy7nc"}]}}}, "files": {"game": [{"name": "setup_elements_and_build_1.0_(86475).exe", "type": "game", "size": "198.08 MB"}]}, "scraped_at": "2026-06-09T15:31:04.190Z"}