{"id": "1633325078", "slug": "final_fantasy_iv_3d_remake", "title": "Final Fantasy IV (3D Remake)", "developer": "Square Enix", "publisher": "Square Enix", "gog_url": "https://www.gog.com/game/final_fantasy_iv_3d_remake", "image": "https://images.gog-statics.com/6bee6cd4d2e7648080ba14f9aad845982d5b92d6ba5884a82d353faca2227958.webp", "background": "c0e80726a61f27e113be93d75c005893ae67e6b2f946db2dfccd7ca07e61050b", "rating": 4.6, "popularity_ranking": 491, "release_timestamp": 1410901200, "genres": ["Adventure", "JRPG", "Role-playing"], "tags": ["Difficult", "Fantasy", "Good Old Game", "Great Soundtrack", "JRPG", "Magic", "Remake", "Retro", "Story Rich", "Third Person", "Turn-Based"], "is_indev": 0, "is_outdated": 0, "last_update": "2026-01-29T19:10:06.000000Z", "current_version": "1.0 GOG v1", "gog_version": "1.0 GOG v1", "is_new": 0, "is_updated": 0, "is_mod": 0, "is_queued": 0, "is_uploading": 0, "infohash": "9bd5e5da7317f53cc602a29616f79e55e53a6f89", "md5_filename": "final_fantasy_iv_3d_remake.md5", "md5_files": [{"hash": "adaffd26b15eab7978821fd47845b234", "filename": "setup_final_fantasy_iv_(3d_remake)_1.0_gog_v1_(87846)-1.bin"}, {"hash": "c959d78fd09eb4de5ac9f3d05c2353ac", "filename": "setup_final_fantasy_iv_(3d_remake)_1.0_gog_v1_(87846).exe"}], "magnet_link": "magnet:?xt=urn:btih:9bd5e5da7317f53cc602a29616f79e55e53a6f89&dn=Final%20Fantasy%20IV%20(3D%20Remake)&tr=udp%3A%2F%2Ftracker.opentrackr.org%3A1337%2Fannounce&tr=udp%3A%2F%2Fexodus.desync.com%3A6969%2Fannounce&tr=udp%3A%2F%2Fopen.stealth.si%3A80%2Fannounce&tr=udp%3A%2F%2Ftracker-udp.gbitt.info%3A80%2Fannounce", "gogdb_url": "https://www.gogdb.org/product/1633325078", "pcgamingwiki_url": "https://pcgamingwiki.com/api/gog.php?page=1633325078", "download_links": {"game": {"gofile": {"id": "gofile", "name": "Gofile", "links": [{"label": "game-final.fantasy.iv.3d.remake-(87846).rar", "link": "https://gofile.io/d/TIhOXg"}]}, "pixeldrain": {"id": "pixeldrain", "name": "Pixeldrain", "links": [{"label": "game-final.fantasy.iv.3d.remake-(87846).rar", "link": "https://pixeldrain.com/u/bVnqHcmm"}]}, "1fichier": {"id": "1fichier", "name": "1fichier", "links": [{"label": "game-final.fantasy.iv.3d.remake-(87846).rar", "link": "https://1fichier.com/?1ec3mr8t9q0l1oajrzja"}]}}}, "files": {"game": [{"name": "setup_final_fantasy_iv_(3d_remake)_1.0_gog_v1_(87846).exe", "type": "game", "size": "1.79 MB"}, {"name": "setup_final_fantasy_iv_(3d_remake)_1.0_gog_v1_(87846)-1.bin", "type": "game", "size": "731.75 MB"}]}, "scraped_at": "2026-06-09T15:25:12.562Z"}