{"id": "1370392202", "slug": "hakuoki_kyoto_winds", "title": "Hakuoki: Kyoto Winds", "developer": "Idea Factory / Design Factory", "publisher": "Idea Factory International", "gog_url": "https://www.gog.com/game/hakuoki_kyoto_winds", "image": "https://images.gog-statics.com/6761e9bd82c833b9bb4b305c4f2b80634d6f39b82d4df43f6b702afc43160e1c.webp", "background": "72c2b115759f05b84f8ac1125b0a25061579bd46b0c2869a86543ed0e0c7cf35", "rating": 4.2, "popularity_ranking": 2795, "release_timestamp": 1503781200, "genres": ["Adventure", "Narrative", "Visual Novel"], "tags": ["Adventure", "Choices Matter", "Dating Sim", "Female Protagonist", "Multiple Endings", "Mystery", "Narrative", "Romance", "Story Rich", "Visual Novel"], "is_indev": 0, "is_outdated": 0, "last_update": "2021-11-14T22:00:17.000000Z", "current_version": "1.0", "gog_version": "1.0", "is_new": 0, "is_updated": 0, "is_mod": 0, "is_queued": 0, "is_uploading": 0, "infohash": null, "md5_filename": "hakuoki_kyoto_winds.md5", "md5_files": [{"hash": "9a52e7228390f5e2541e857921c4c77c", "filename": "hakuoki_kyoto_winds_art_collection.zip"}, {"hash": "b53a7f6bf5357435c2722a68f09fba89", "filename": "hakuoki_kyoto_winds_ost.zip"}, {"hash": "1edd9280f40bda7b58c2ce78c01e8254", "filename": "hakuoki_kyoto_winds_wallpapers.zip"}, {"hash": "4bb02c6fefb76187b82322b4a78183af", "filename": "setup_hakuoki_kyoto_winds_-_winds_treasure_box_1.0_(49572).exe"}, {"hash": "05a04afa5a75bd5c234066a5cf14bcda", "filename": "setup_hakuoki_kyoto_winds_1.0_(49572)-1.bin"}, {"hash": "994204e1bb34bc3eb5574cddeb865dc9", "filename": "setup_hakuoki_kyoto_winds_1.0_(49572)-2.bin"}, {"hash": "3ede15aac3cadece337099c10d00babf", "filename": "setup_hakuoki_kyoto_winds_1.0_(49572).exe"}], "magnet_link": null, "gogdb_url": "https://www.gogdb.org/product/1370392202", "pcgamingwiki_url": "https://pcgamingwiki.com/api/gog.php?page=1370392202", "download_links": {"goodie": {"gofile": {"id": "gofile", "name": "Gofile", "links": [{"label": "extras-hakuoki.kyoto.winds.rar", "link": "https://gofile.io/d/CFouqL"}]}, "pixeldrain": {"id": "pixeldrain", "name": "Pixeldrain", "links": [{"label": "extras-hakuoki.kyoto.winds.rar", "link": "https://pixeldrain.com/u/R8Y3aKZs"}]}, "1fichier": {"id": "1fichier", "name": "1fichier", "links": [{"label": "extras-hakuoki.kyoto.winds.rar", "link": "https://1fichier.com/?chliiukzjaz1zrpevgo4"}]}}, "game": {"gofile": {"id": "gofile", "name": "Gofile", "links": [{"label": "game-hakuoki.kyoto.winds-(49572).rar", "link": "https://gofile.io/d/efGBw7"}]}, "pixeldrain": {"id": "pixeldrain", "name": "Pixeldrain", "links": [{"label": "game-hakuoki.kyoto.winds-(49572).rar", "link": "https://pixeldrain.com/u/PnkdGSkG"}]}, "1fichier": {"id": "1fichier", "name": "1fichier", "links": [{"label": "game-hakuoki.kyoto.winds-(49572).rar", "link": "https://1fichier.com/?pgd1nvy73xv1tr9vurjs"}]}}}, "files": {"game": [{"name": "setup_hakuoki_kyoto_winds_1.0_(49572).exe", "type": "game", "size": "937.08 KB"}, {"name": "setup_hakuoki_kyoto_winds_1.0_(49572)-1.bin", "type": "game", "size": "4 GB"}, {"name": "setup_hakuoki_kyoto_winds_1.0_(49572)-2.bin", "type": "game", "size": "3.79 GB"}, {"name": "setup_hakuoki_kyoto_winds_-_winds_treasure_box_1.0_(49572).exe", "type": "game", "size": "107.52 MB"}], "goodie": [{"name": "hakuoki_kyoto_winds_art_collection.zip", "type": "goodie", "size": "289.31 MB"}, {"name": "hakuoki_kyoto_winds_ost.zip", "type": "goodie", "size": "82.88 MB"}, {"name": "hakuoki_kyoto_winds_wallpapers.zip", "type": "goodie", "size": "43.42 MB"}]}, "scraped_at": "2026-06-09T15:16:54.996Z"}