{"id": "2004253604", "slug": "into_the_breach", "title": "Into the Breach", "developer": "Subset Games", "publisher": "Subset Games", "gog_url": "https://www.gog.com/game/into_the_breach", "image": "https://images.gog-statics.com/42907ded32893ac131ec96bd98867a318465a6a9aa8824e92065f1437dfc0def.webp", "background": "3473fe0efad4d38c19c89ef594e4d112d479df14d4e813c7427edeac19197274", "rating": 4.6, "popularity_ranking": 954, "release_timestamp": 1519682400, "genres": ["Sci-fi", "Simulation", "Strategy"], "tags": ["Great Soundtrack", "Indie", "Isometric", "Pixel Graphics", "Procedural Generation", "Puzzle", "Roguelike", "Roguelite", "Sci-fi", "Science", "Simulation", "Strategy", "Tactical", "Turn-Based"], "is_indev": 0, "is_outdated": 0, "last_update": "2024-03-18T04:19:55.000000Z", "current_version": "1.2.93", "gog_version": "1.2.93", "is_new": 0, "is_updated": 0, "is_mod": 0, "is_queued": 0, "is_uploading": 0, "infohash": null, "md5_filename": "into_the_breach.md5", "md5_files": [{"hash": "ccdc0621eafbb94ba061b0b02c8149c4", "filename": "setup_into_the_breach_1.2.93_(71867).exe"}], "magnet_link": null, "gogdb_url": "https://www.gogdb.org/product/2004253604", "pcgamingwiki_url": "https://pcgamingwiki.com/api/gog.php?page=2004253604", "download_links": {"game": {"gofile": {"id": "gofile", "name": "Gofile", "links": [{"label": "game-into.the.breach-(71867).rar", "link": "https://gofile.io/d/2F9qAv"}]}, "fileditch": {"id": "fileditch", "name": "FileDitch", "links": [{"label": "game-into.the.breach-(71867).rar", "link": "https://small.fileditchstuff.me/s14/cgRskBUrabBNYlxIIgtA.rar"}]}, "pixeldrain": {"id": "pixeldrain", "name": "Pixeldrain", "links": [{"label": "game-into.the.breach-(71867).rar", "link": "https://pixeldrain.com/u/ufkwhM6w"}]}, "1fichier": {"id": "1fichier", "name": "1fichier", "links": [{"label": "game-into.the.breach-(71867).rar", "link": "https://1fichier.com/?pldyg40fogyx0mhueckk"}]}}}, "files": {"game": [{"name": "setup_into_the_breach_1.2.93_(71867).exe", "type": "game", "size": "444.07 MB"}]}, "scraped_at": "2026-06-09T15:07:39.954Z"}