{"id": "1207658645", "slug": "mdk_2", "title": "MDK 2", "developer": "BioWare", "publisher": "Interplay", "gog_url": "https://www.gog.com/game/mdk_2", "image": "https://images.gog-statics.com/727c27ece9944d7873210bee007a94f76783fb68afbb1d1fc33fe5cde826f5cf.webp", "background": "bc584ddf8934cac483a41a04a6d21270620c0f3b795a1eaeeb746e4684eaf891", "rating": 4.3, "popularity_ranking": 3104, "release_timestamp": 959634000, "genres": ["Action", "Sci-fi", "TPP"], "tags": ["Action", "Atmospheric", "Classic", "Cyberpunk", "Difficult", "Dog", "Funny", "Platformer", "Sci-fi", "Science", "Sniper", "Third Person"], "is_indev": 0, "is_outdated": 0, "last_update": "2019-11-08T20:53:06.000000Z", "current_version": "1.0003 v2", "gog_version": "1.0003 v2", "is_new": 0, "is_updated": 0, "is_mod": 0, "is_queued": 0, "is_uploading": 0, "infohash": null, "md5_filename": "mdk_2.md5", "md5_files": [{"hash": "c63c231cb2d5bc8d5898c49abb61f44a", "filename": "mdk2_soundtrack.zip"}, {"hash": "cf8f7171a4406a8d86c1576fdf53a6b3", "filename": "mdk_2_artworks.zip"}, {"hash": "4bca161d7a106c65dc232ab3bb4bb56f", "filename": "mdk_2_avatar.zip"}, {"hash": "f93ce3a985ed121b09ac1274f3fe5283", "filename": "mdk_2_manual.zip"}, {"hash": "76a70c9b5f28c4feb211d26d89b2840a", "filename": "mdk_2_storyboard_artwork.zip"}, {"hash": "81bb0430d729161f0d3cfcc5c4fa5107", "filename": "mdk_2_wallpapers.zip"}, {"hash": "a6dd8236671a4f073c413167a3464205", "filename": "setup_mdk2_russian_2.1.0.3.exe"}, {"hash": "019c777cb268e899f5c526c83aca3f44", "filename": "setup_mdk_2_1.0003_v2_(33758).exe"}], "magnet_link": null, "gogdb_url": "https://www.gogdb.org/product/1207658645", "pcgamingwiki_url": "https://pcgamingwiki.com/api/gog.php?page=1207658645", "download_links": {"goodie": {"gofile": {"id": "gofile", "name": "Gofile", "links": [{"label": "extras-mdk.2.rar", "link": "https://gofile.io/d/iCLWO2"}]}, "fileditch": {"id": "fileditch", "name": "FileDitch", "links": [{"label": "extras-mdk.2.rar", "link": "https://small.fileditchstuff.me/s13/aJcHNiyhzybyLMlTKFHJ.rar"}]}, "pixeldrain": {"id": "pixeldrain", "name": "Pixeldrain", "links": [{"label": "extras-mdk.2.rar", "link": "https://pixeldrain.com/u/WUnLMbpJ"}]}, "1fichier": {"id": "1fichier", "name": "1fichier", "links": [{"label": "extras-mdk.2.rar", "link": "https://1fichier.com/?8kqisl1e47wutgulzm3y"}]}}, "game": {"gofile": {"id": "gofile", "name": "Gofile", "links": [{"label": "game-mdk.2-(33758).rar", "link": "https://gofile.io/d/77Nlyz"}]}, "fileditch": {"id": "fileditch", "name": "FileDitch", "links": [{"label": "game-mdk.2-(33758).rar", "link": "https://small.fileditchstuff.me/s13/IwfsGRHVGYAthHxzzdC.rar"}]}, "pixeldrain": {"id": "pixeldrain", "name": "Pixeldrain", "links": [{"label": "game-mdk.2-(33758).rar", "link": "https://pixeldrain.com/u/pHvjk2zn"}]}, "1fichier": {"id": "1fichier", "name": "1fichier", "links": [{"label": "game-mdk.2-(33758).rar", "link": "https://1fichier.com/?hgw5v8mrmkm70sa7240n"}]}}}, "files": {"game": [{"name": "setup_mdk_2_1.0003_v2_(33758).exe", "type": "game", "size": "206.33 MB"}], "goodie": [{"name": "mdk2_soundtrack.zip", "type": "goodie", "size": "92.25 MB"}, {"name": "mdk_2_artworks.zip", "type": "goodie", "size": "1.41 MB"}, {"name": "mdk_2_avatar.zip", "type": "goodie", "size": "38.04 KB"}, {"name": "mdk_2_manual.zip", "type": "goodie", "size": "4.93 MB"}, {"name": "mdk_2_storyboard_artwork.zip", "type": "goodie", "size": "1.06 MB"}, {"name": "mdk_2_wallpapers.zip", "type": "goodie", "size": "8.24 MB"}, {"name": "setup_mdk2_russian_2.1.0.3.exe", "type": "goodie", "size": "260.74 MB"}]}, "scraped_at": "2026-06-09T14:52:52.727Z"}