{"id": "1688255471", "slug": "mokoko_x", "title": "Mokoko X", "developer": "NAISU", "publisher": "MediBang Games", "gog_url": "https://www.gog.com/game/mokoko_x", "image": "https://images.gog-statics.com/d88e8bf29e977445255da504d9d3d5ad146d139d4a6fcd522ee03bdc823e7776.webp", "background": "fecf3325382dd7635780c46d837b759322f63e07a982df1ddfc409ca96f04cd7", "rating": 2.4, "popularity_ranking": 4254, "release_timestamp": 1649278800, "genres": ["Arcade", "Shoot 'em Up", "Shooter"], "tags": ["2D", "Arcade", "Bullet Hell", "Dating Sim", "Funny", "Mature", "NSFW", "Nudity", "Sexual Content", "Shoot'EmUp", "Shooter", "Story Rich", "Top-Down"], "is_indev": 0, "is_outdated": 0, "last_update": "2023-06-13T21:55:39.000000Z", "current_version": "1.03", "gog_version": "1.03", "is_new": 0, "is_updated": 0, "is_mod": 0, "is_queued": 0, "is_uploading": 0, "infohash": null, "md5_filename": "mokoko_x.md5", "md5_files": [{"hash": "6e143b938017d344d80f7d1b7de3e7fa", "filename": "mokoko_x_artwork.zip"}, {"hash": "2c31da05303f715a3e03fcb0b3e4fc0d", "filename": "mokoko_x_soundtrack.zip"}, {"hash": "cde27e13294afa7ce4b8617c3069c53c", "filename": "setup_mokoko_x_1.03_(63840).exe"}, {"hash": "944f46518f789821d610e73783f90193", "filename": "setup_mokoko_x_unrated_1.03_(63840).exe"}], "magnet_link": null, "gogdb_url": "https://www.gogdb.org/product/1688255471", "pcgamingwiki_url": "https://pcgamingwiki.com/api/gog.php?page=1688255471", "download_links": {"goodie": {"gofile": {"id": "gofile", "name": "Gofile", "links": [{"label": "extras-mokoko.x.rar", "link": "https://gofile.io/d/PlQp1i"}]}, "pixeldrain": {"id": "pixeldrain", "name": "Pixeldrain", "links": [{"label": "extras-mokoko.x.rar", "link": "https://pixeldrain.com/u/KQ8RmsfZ"}]}, "1fichier": {"id": "1fichier", "name": "1fichier", "links": [{"label": "extras-mokoko.x.rar", "link": "https://1fichier.com/?jboppba2f1jxo9oj83gx"}]}}, "game": {"gofile": {"id": "gofile", "name": "Gofile", "links": [{"label": "game-mokoko.x-(63840).rar", "link": "https://gofile.io/d/m6PmHd"}]}, "pixeldrain": {"id": "pixeldrain", "name": "Pixeldrain", "links": [{"label": "game-mokoko.x-(63840).rar", "link": "https://pixeldrain.com/u/vNyjgvVv"}]}, "1fichier": {"id": "1fichier", "name": "1fichier", "links": [{"label": "game-mokoko.x-(63840).rar", "link": "https://1fichier.com/?uytpbnjwb2r2lipiq4zj"}]}}}, "files": {"game": [{"name": "setup_mokoko_x_1.03_(63840).exe", "type": "game", "size": "566.91 MB"}, {"name": "setup_mokoko_x_unrated_1.03_(63840).exe", "type": "game", "size": "520.6 MB"}], "goodie": [{"name": "mokoko_x_artwork.zip", "type": "goodie", "size": "353.36 MB"}, {"name": "mokoko_x_soundtrack.zip", "type": "goodie", "size": "184.58 MB"}]}, "scraped_at": "2026-06-09T14:50:03.562Z"}