{"id": "1586537281", "slug": "mortal_shell", "title": "Mortal Shell", "developer": "Cold Symmetry", "publisher": "Playstack", "gog_url": "https://www.gog.com/game/mortal_shell", "image": "https://images.gog-statics.com/644260d5fc6269d149448d6bee821de689d4cce075323b5a51e667553000beed.webp", "background": "40cf314057761b4bdd3222ced49084f0f95c13d7954dfe79435124f7dcce41ab", "rating": 3.7, "popularity_ranking": 2272, "release_timestamp": 1629234000, "genres": ["Action", "Fantasy", "Role-playing"], "tags": ["Action", "Atmospheric", "Dark", "Difficult", "Fantasy", "Role-playing", "Souls-like", "Third Person", "Violent"], "is_indev": 0, "is_outdated": 0, "last_update": "2021-08-28T03:07:35.000000Z", "current_version": "1.014707", "gog_version": "1.014707", "is_new": 0, "is_updated": 0, "is_mod": 0, "is_queued": 0, "is_uploading": 0, "infohash": null, "md5_filename": "mortal_shell.md5", "md5_files": [{"hash": "87a10de7c30c37975d0fc1522b84beb1", "filename": "setup_mortal_shell_-_the_virtuous_cycle_1.014707_(64bit)_(49535).exe"}, {"hash": "86c4be06cad0e0290eddb9df40ea258a", "filename": "setup_mortal_shell_1.014707_(64bit)_(49535)-1.bin"}, {"hash": "d253964575de78018b7369b0a8b694f4", "filename": "setup_mortal_shell_1.014707_(64bit)_(49535)-2.bin"}, {"hash": "900f78bb3443ccea519fc166dab38ca3", "filename": "setup_mortal_shell_1.014707_(64bit)_(49535)-3.bin"}, {"hash": "7806d4960b766255e7b2c1f7f2168ea5", "filename": "setup_mortal_shell_1.014707_(64bit)_(49535).exe"}], "magnet_link": null, "gogdb_url": "https://www.gogdb.org/product/1586537281", "pcgamingwiki_url": "https://pcgamingwiki.com/api/gog.php?page=1586537281", "download_links": {"game": {"gofile": {"id": "gofile", "name": "Gofile", "links": [{"label": "game-mortal.shell-(49535).rar", "link": "https://gofile.io/d/EIfwvk"}]}, "pixeldrain": {"id": "pixeldrain", "name": "Pixeldrain", "links": [{"label": "game-mortal.shell-(49535).rar", "link": "https://pixeldrain.com/u/abJzQWgN"}]}, "1fichier": {"id": "1fichier", "name": "1fichier", "links": [{"label": "game-mortal.shell-(49535).rar", "link": "https://1fichier.com/?7xuryvrz7o09i4uumezq"}]}}}, "files": {"game": [{"name": "setup_mortal_shell_1.014707_(64bit)_(49535).exe", "type": "game", "size": "937.95 KB"}, {"name": "setup_mortal_shell_1.014707_(64bit)_(49535)-1.bin", "type": "game", "size": "4 GB"}, {"name": "setup_mortal_shell_1.014707_(64bit)_(49535)-2.bin", "type": "game", "size": "4 GB"}, {"name": "setup_mortal_shell_1.014707_(64bit)_(49535)-3.bin", "type": "game", "size": "482.04 MB"}, {"name": "setup_mortal_shell_-_the_virtuous_cycle_1.014707_(64bit)_(49535).exe", "type": "game", "size": "6.18 MB"}]}, "scraped_at": "2026-06-09T14:48:50.935Z"}