{"id": "1816577311", "slug": "primal_hearts_2", "title": "Primal Hearts 2", "developer": "Marmalade", "publisher": "Shiravune", "gog_url": "https://www.gog.com/game/primal_hearts_2", "image": "https://images.gog-statics.com/372d6b6e726cd0e311870678125f1ab12fdd16927dccdb3264917256f724128b.webp", "background": "306ba82abc5698b195b0b2cc38928c096f52efb71f36af43e8b58daf17abd0d2", "rating": 5.0, "popularity_ranking": 636, "release_timestamp": 1739311200, "genres": ["Adventure", "JRPG", "Visual Novel"], "tags": ["2D", "Adventure", "Casual", "Choices Matter", "Choose Your Own Adventure", "Comedy", "Dating Sim", "Funny", "JRPG", "LifeSim", "Martial Arts", "Mature", "Multiple Endings", "NSFW", "Narrative", "Nature", "Nudity", "Relaxing", "Romance", "Sexual Content", "Story Rich", "Text-Based", "Visual Novel"], "is_indev": 0, "is_outdated": 0, "last_update": "2025-06-02T14:20:55.000000Z", "current_version": "1.0.1", "gog_version": "1.0.1", "is_new": 0, "is_updated": 0, "is_mod": 0, "is_queued": 0, "is_uploading": 0, "infohash": "cfab4c632e577149f205ab99d3c1554143e9b96f", "md5_filename": "primal_hearts_2.md5", "md5_files": [{"hash": "de415852792d61ec78e955ea6db7ee3c", "filename": "setup_primal_hearts_2_1.0.1_(82442)-1.bin"}, {"hash": "6a15fa4f5677a88ce46e9abb8fd4a1bc", "filename": "setup_primal_hearts_2_1.0.1_(82442).exe"}, {"hash": "6188e7bdd40e4155bf7aa96c4788d46f", "filename": "setup_primal_hearts_2_unrated_1.0.1_(82442)-1.bin"}, {"hash": "ad9c6458a5ec1d5af5df0a317a414fef", "filename": "setup_primal_hearts_2_unrated_1.0.1_(82442).exe"}], "magnet_link": "magnet:?xt=urn:btih:cfab4c632e577149f205ab99d3c1554143e9b96f&dn=Primal%20Hearts%202&tr=udp%3A%2F%2Ftracker.opentrackr.org%3A1337%2Fannounce&tr=udp%3A%2F%2Fexodus.desync.com%3A6969%2Fannounce&tr=udp%3A%2F%2Fopen.stealth.si%3A80%2Fannounce&tr=udp%3A%2F%2Ftracker-udp.gbitt.info%3A80%2Fannounce", "gogdb_url": "https://www.gogdb.org/product/1816577311", "pcgamingwiki_url": "https://pcgamingwiki.com/api/gog.php?page=1816577311", "download_links": {"game": {"gofile": {"id": "gofile", "name": "Gofile", "links": [{"label": "game-primal.hearts.2-(82442).rar", "link": "https://gofile.io/d/q5kVCa"}]}, "pixeldrain": {"id": "pixeldrain", "name": "Pixeldrain", "links": [{"label": "game-primal.hearts.2-(82442).rar", "link": "https://pixeldrain.com/u/aRyTN2gb"}]}, "1fichier": {"id": "1fichier", "name": "1fichier", "links": [{"label": "game-primal.hearts.2-(82442).rar", "link": "https://1fichier.com/?eixw6ridrywg5b14wznz"}]}}}, "files": {"game": [{"name": "setup_primal_hearts_2_1.0.1_(82442).exe", "type": "game", "size": "797.59 KB"}, {"name": "setup_primal_hearts_2_1.0.1_(82442)-1.bin", "type": "game", "size": "3.53 GB"}, {"name": "setup_primal_hearts_2_unrated_1.0.1_(82442).exe", "type": "game", "size": "789.6 KB"}, {"name": "setup_primal_hearts_2_unrated_1.0.1_(82442)-1.bin", "type": "game", "size": "3.05 GB"}]}, "scraped_at": "2026-06-09T14:36:39.123Z"}