{"id": "1876835821", "slug": "rocket_knight_adventures_resparked", "title": "Rocket Knight Adventures: Re-Sparked", "developer": "Limited Run Games", "publisher": "KONAMI", "gog_url": "https://www.gog.com/game/rocket_knight_adventures_resparked", "image": "https://images.gog-statics.com/f5a73d00c21bf551b8b7e9e0ba2113d97033925f5f51c78384778e783680122d.webp", "background": "1b192619c315a13f8788c11975a519e0c20571db46b1517098eb1c3d3843a630", "rating": 5.0, "popularity_ranking": 1617, "release_timestamp": 1718053200, "genres": ["Action", "Adventure", "Platformer"], "tags": ["2D", "Fantasy", "Platformer", "Retro"], "is_indev": 0, "is_outdated": 0, "last_update": "2026-05-29T20:21:07.000000Z", "current_version": "RC3", "gog_version": "RC3", "is_new": 1, "is_updated": 0, "is_mod": 0, "is_queued": 0, "is_uploading": 0, "infohash": "251232b1aecc4ae2b974f92e16be29fdef7e6a95", "md5_filename": "rocket_knight_adventures_resparked.md5", "md5_files": [{"hash": "6c297d44583bfbd72df7542557e06fc7", "filename": "setup_rocket_knight_adventures_re-sparked_rc3_(87351)-1.bin"}, {"hash": "241c124cc642f5896f8ad5cc2f8059fb", "filename": "setup_rocket_knight_adventures_re-sparked_rc3_(87351).exe"}], "magnet_link": "magnet:?xt=urn:btih:251232b1aecc4ae2b974f92e16be29fdef7e6a95&dn=Rocket%20Knight%20Adventures%3A%20Re-Sparked&tr=udp%3A%2F%2Ftracker.opentrackr.org%3A1337%2Fannounce&tr=udp%3A%2F%2Fexodus.desync.com%3A6969%2Fannounce&tr=udp%3A%2F%2Fopen.stealth.si%3A80%2Fannounce&tr=udp%3A%2F%2Ftracker-udp.gbitt.info%3A80%2Fannounce", "gogdb_url": "https://www.gogdb.org/product/1876835821", "pcgamingwiki_url": "https://pcgamingwiki.com/api/gog.php?page=1876835821", "download_links": {"game": {"fileq": {"id": "fileq", "name": "FileQ", "links": [{"label": "game-rocket.knight.adventures.resparked-(87351).rar", "link": "https://fileq.net/eteccvixtj9a"}]}, "transferit": {"id": "transferit", "name": "Transfer.it", "links": [{"label": "game-rocket.knight.adventures.resparked-(87351).rar", "link": "https://transfer.it/t/bNmmP343GLRY"}]}, "gofile": {"id": "gofile", "name": "Gofile", "links": [{"label": "game-rocket.knight.adventures.resparked-(87351).rar", "link": "https://gofile.io/d/Ca84Os"}]}, "fileditch": {"id": "fileditch", "name": "FileDitch", "links": [{"label": "game-rocket.knight.adventures.resparked-(87351).rar", "link": "https://fileditchfiles.me/file.php?f=/alpha6/e8feb20e781671291ddf/game-rocket.knight.adventures.resparked-%2887351%29.rar"}]}, "pixeldrain": {"id": "pixeldrain", "name": "Pixeldrain", "links": [{"label": "game-rocket.knight.adventures.resparked-(87351).rar", "link": "https://pixeldrain.com/u/XuG1zXTH"}]}, "1fichier": {"id": "1fichier", "name": "1fichier", "links": [{"label": "game-rocket.knight.adventures.resparked-(87351).rar", "link": "https://1fichier.com/?z01o7r344k12eohrfyr5"}]}}}, "files": {"game": [{"name": "setup_rocket_knight_adventures_re-sparked_rc3_(87351).exe", "type": "game", "size": "867.62 KB"}, {"name": "setup_rocket_knight_adventures_re-sparked_rc3_(87351)-1.bin", "type": "game", "size": "2.42 GB"}]}, "scraped_at": "2026-06-09T14:26:12.845Z"}