{"id": "1973516426", "slug": "seal_of_evil", "title": "Seal of Evil", "developer": "Object Software Limited", "publisher": "Strategy First", "gog_url": "https://www.gog.com/game/seal_of_evil", "image": "https://images.gog-statics.com/6bab93874372626c33b82f36d7661ea48d6e7fc73065a5d6f8e9f53a1860f11a.webp", "background": "f46742a5f1c1eeb5c3ced64dc2ad835d80c67e8db3ebfd451daf68eb90e8139c", "rating": 4.1, "popularity_ranking": 4395, "release_timestamp": 1097787600, "genres": ["Action", "Fantasy", "Role-playing"], "tags": ["Action", "Fantasy", "Role-playing"], "is_indev": 0, "is_outdated": 0, "last_update": "2023-09-24T15:07:07.000000Z", "current_version": "1.06", "gog_version": "1.06", "is_new": 0, "is_updated": 0, "is_mod": 0, "is_queued": 0, "is_uploading": 0, "infohash": null, "md5_filename": "seal_of_evil.md5", "md5_files": [{"hash": "6b65a61fa77d78ad4c61f465cbf71fd1", "filename": "setup_seal_of_evil_1.06_(66125).exe"}], "magnet_link": null, "gogdb_url": "https://www.gogdb.org/product/1973516426", "pcgamingwiki_url": "https://pcgamingwiki.com/api/gog.php?page=1973516426", "download_links": {"game": {"gofile": {"id": "gofile", "name": "Gofile", "links": [{"label": "game-seal.of.evil-(66125).rar", "link": "https://gofile.io/d/KgHTKN"}]}, "pixeldrain": {"id": "pixeldrain", "name": "Pixeldrain", "links": [{"label": "game-seal.of.evil-(66125).rar", "link": "https://pixeldrain.com/u/gcAhM8HC"}]}, "1fichier": {"id": "1fichier", "name": "1fichier", "links": [{"label": "game-seal.of.evil-(66125).rar", "link": "https://1fichier.com/?k8is7ie6bo3qd3k8nzt5"}]}}}, "files": {"game": [{"name": "setup_seal_of_evil_1.06_(66125).exe", "type": "game", "size": "1.54 GB"}]}, "scraped_at": "2026-06-09T14:21:13.206Z"}