{"id": "1402489296", "slug": "shattered_tale_of_the_forgotten_king", "title": "Shattered - Tale of the Forgotten King", "developer": "Redlock Studio", "publisher": "Redlock Studio", "gog_url": "https://www.gog.com/game/shattered_tale_of_the_forgotten_king", "image": "https://images.gog-statics.com/463071bd0db54b48c017ec5f5cd9bb1507c214ceafbfd7d4ea5d338e41b3c8fe.webp", "background": "3a8fa140a15e1d5c29ac54c4d90c141eeba69ecf752ba6365028144c5c8a274c", "rating": 3.3, "popularity_ranking": 4724, "release_timestamp": 1613512800, "genres": ["Action", "Fantasy", "Role-playing"], "tags": ["Action", "Dark", "Fantasy", "Role-playing", "Third Person"], "is_indev": 0, "is_outdated": 0, "last_update": "2021-07-15T15:19:04.000000Z", "current_version": "1.3.00", "gog_version": "1.3.00", "is_new": 0, "is_updated": 0, "is_mod": 0, "is_queued": 0, "is_uploading": 0, "infohash": null, "md5_filename": "shattered_tale_of_the_forgotten_king.md5", "md5_files": [{"hash": "ee5bf5d8af23c99212487baa84356dfa", "filename": "setup_shattered_-_tale_of_the_forgotten_king_1.3.00_(64bit)_(48470)-1.bin"}, {"hash": "887746952e585ed81274973eb7cd3059", "filename": "setup_shattered_-_tale_of_the_forgotten_king_1.3.00_(64bit)_(48470)-2.bin"}, {"hash": "02e581db8b1347fb0bd100dcd6e745d9", "filename": "setup_shattered_-_tale_of_the_forgotten_king_1.3.00_(64bit)_(48470)-3.bin"}, {"hash": "4871c9c8b15861e6e1448543c09ff333", "filename": "setup_shattered_-_tale_of_the_forgotten_king_1.3.00_(64bit)_(48470).exe"}], "magnet_link": null, "gogdb_url": "https://www.gogdb.org/product/1402489296", "pcgamingwiki_url": "https://pcgamingwiki.com/api/gog.php?page=1402489296", "download_links": {"game": {"pixeldrain": {"id": "pixeldrain", "name": "Pixeldrain", "links": [{"label": "game-shattered.tale.of.the.forgotten.king-(48470).rar", "link": "https://pixeldrain.com/u/9pFTPgDo"}]}, "1fichier": {"id": "1fichier", "name": "1fichier", "links": [{"label": "game-shattered.tale.of.the.forgotten.king-(48470).rar", "link": "https://1fichier.com/?puldkrwyike16st870uq"}]}}}, "files": {"game": [{"name": "setup_shattered_-_tale_of_the_forgotten_king_1.3.00_(64bit)_(48470).exe", "type": "game", "size": "926.78 KB"}, {"name": "setup_shattered_-_tale_of_the_forgotten_king_1.3.00_(64bit)_(48470)-1.bin", "type": "game", "size": "4 GB"}, {"name": "setup_shattered_-_tale_of_the_forgotten_king_1.3.00_(64bit)_(48470)-2.bin", "type": "game", "size": "4 GB"}, {"name": "setup_shattered_-_tale_of_the_forgotten_king_1.3.00_(64bit)_(48470)-3.bin", "type": "game", "size": "3.32 GB"}]}, "scraped_at": "2026-06-09T14:17:57.508Z"}