{"id": "1705092808", "slug": "train_valley_2", "title": "Train Valley 2", "developer": "Alexey Davydov, Sergey Dvoynikov, Timofey Shargorodskiy", "publisher": "Flazm, META Publishing", "gog_url": "https://www.gog.com/game/train_valley_2", "image": "https://images.gog-statics.com/13f54841f63d458105fd74297ce771c4e682435289f490cb450f6d21b86a7098.webp", "background": "7b3f9db6a27c000f7069fd883a25b6617190275de9e99fecadfdf0c6f2b0d408", "rating": 4.2, "popularity_ranking": 1237, "release_timestamp": 1555275600, "genres": ["Building", "Managerial", "Simulation"], "tags": ["Building", "Casual", "LevelEditor", "Management", "Managerial", "Puzzle", "Relaxing", "Resource Management", "Simulation", "Top-Down", "Trains", "Transportation"], "is_indev": 0, "is_outdated": 0, "last_update": "2026-04-24T00:48:07.000000Z", "current_version": "1.9", "gog_version": "1.9", "is_new": 0, "is_updated": 0, "is_mod": 0, "is_queued": 0, "is_uploading": 0, "infohash": "31167325c197f4973ba99c0a7f8ff70be6a59229", "md5_filename": "train_valley_2.md5", "md5_files": [{"hash": "6b2f4fb6ac6f5ab1fd0940a1dda9b4d4", "filename": "setup_train_valley_2_-_editors_bulletin_1.9_(64bit)_(89848).exe"}, {"hash": "9dbb2cc0b7fb184912557c2983021e9d", "filename": "setup_train_valley_2_-_japanese_trails_1.9_(64bit)_(89848).exe"}, {"hash": "8f0b664273c03ccadb6af90a091b03d0", "filename": "setup_train_valley_2_-_passenger_flow_1.9_(64bit)_(89848).exe"}, {"hash": "8f9af6a159df69f0df000067d0ec6349", "filename": "setup_train_valley_2_-_patent_pending_1.9_(64bit)_(89848).exe"}, {"hash": "abd68b9e99feab6d2f317e33dcd6061a", "filename": "setup_train_valley_2_-_the_pandeia_project_1.9_(64bit)_(89848).exe"}, {"hash": "23d2a4bd6142d8fdb7e00d9f67af45f6", "filename": "setup_train_valley_2_1.9_(64bit)_(89848).exe"}, {"hash": "1b969519ba60b5e6643057a0c8b9879c", "filename": "setup_train_valley_2_myths__rails_1.9_(64bit)_(89848).exe"}, {"hash": "b384389722f90634129a2f7017fb7168", "filename": "setup_train_valley_2_workshop_gems_-_amethyst_1.9_(64bit)_(89848).exe"}, {"hash": "231532d22003de155c38dd8b41cead90", "filename": "setup_train_valley_2_workshop_gems_-_emerald_1.9_(64bit)_(89848).exe"}, {"hash": "cae3267c94f92e41a1ea51521d26b474", "filename": "setup_train_valley_2_workshop_gems_-_ruby_1.9_(64bit)_(89848).exe"}, {"hash": "c8f9f87fc9d05fc251ca79d7b162d727", "filename": "setup_train_valley_2_workshop_gems_-_sapphire_1.9_(64bit)_(89848).exe"}, {"hash": "eda6b59a9f234e32e3aaf1fc9eee9992", "filename": "train_valley_2_ost_mp3.zip"}], "magnet_link": "magnet:?xt=urn:btih:31167325c197f4973ba99c0a7f8ff70be6a59229&dn=Train%20Valley%202&tr=udp%3A%2F%2Ftracker.opentrackr.org%3A1337%2Fannounce&tr=udp%3A%2F%2Fexodus.desync.com%3A6969%2Fannounce&tr=udp%3A%2F%2Fopen.stealth.si%3A80%2Fannounce&tr=udp%3A%2F%2Ftracker-udp.gbitt.info%3A80%2Fannounce", "gogdb_url": "https://www.gogdb.org/product/1705092808", "pcgamingwiki_url": "https://pcgamingwiki.com/api/gog.php?page=1705092808", "download_links": {"goodie": {"fileq": {"id": "fileq", "name": "FileQ", "links": [{"label": "extras-train.valley.2.rar", "link": "https://fileq.net/pqv0k08xxhqx"}]}, "transferit": {"id": "transferit", "name": "Transfer.it", "links": [{"label": "extras-train.valley.2.rar", "link": "https://transfer.it/t/TLxEmmo1zLqS"}]}, "gofile": {"id": "gofile", "name": "Gofile", "links": [{"label": "extras-train.valley.2.rar", "link": "https://gofile.io/d/MoYr1Z"}]}, "pixeldrain": {"id": "pixeldrain", "name": "Pixeldrain", "links": [{"label": "extras-train.valley.2.rar", "link": "https://pixeldrain.com/u/PC9o66W4"}]}}, "game": {"fileq": {"id": "fileq", "name": "FileQ", "links": [{"label": "game-train.valley.2-(89848).rar", "link": "https://fileq.net/icfr47bc8m4l"}]}, "transferit": {"id": "transferit", "name": "Transfer.it", "links": [{"label": "game-train.valley.2-(89848).rar", "link": "https://transfer.it/t/FOCvbqpjiDLL"}]}, "gofile": {"id": "gofile", "name": "Gofile", "links": [{"label": "game-train.valley.2-(89848).rar", "link": "https://gofile.io/d/yi3x44"}]}, "pixeldrain": {"id": "pixeldrain", "name": "Pixeldrain", "links": [{"label": "game-train.valley.2-(89848).rar", "link": "https://pixeldrain.com/u/PDHEpCJo"}]}}}, "files": {"game": [{"name": "setup_train_valley_2_1.9_(64bit)_(89848).exe", "type": "game", "size": "419.29 MB"}, {"name": "setup_train_valley_2_myths__rails_1.9_(64bit)_(89848).exe", "type": "game", "size": "9.62 MB"}, {"name": "setup_train_valley_2_workshop_gems_-_amethyst_1.9_(64bit)_(89848).exe", "type": "game", "size": "10.52 MB"}, {"name": "setup_train_valley_2_workshop_gems_-_emerald_1.9_(64bit)_(89848).exe", "type": "game", "size": "9.34 MB"}, {"name": "setup_train_valley_2_workshop_gems_-_ruby_1.9_(64bit)_(89848).exe", "type": "game", "size": "9.11 MB"}, {"name": "setup_train_valley_2_workshop_gems_-_sapphire_1.9_(64bit)_(89848).exe", "type": "game", "size": "9.82 MB"}, {"name": "setup_train_valley_2_-_editors_bulletin_1.9_(64bit)_(89848).exe", "type": "game", "size": "7.28 MB"}, {"name": "setup_train_valley_2_-_japanese_trails_1.9_(64bit)_(89848).exe", "type": "game", "size": "7.31 MB"}, {"name": "setup_train_valley_2_-_passenger_flow_1.9_(64bit)_(89848).exe", "type": "game", "size": "8.94 MB"}, {"name": "setup_train_valley_2_-_patent_pending_1.9_(64bit)_(89848).exe", "type": "game", "size": "7.92 MB"}, {"name": "setup_train_valley_2_-_the_pandeia_project_1.9_(64bit)_(89848).exe", "type": "game", "size": "11.22 MB"}], "goodie": [{"name": "train_valley_2_ost_mp3.zip", "type": "goodie", "size": "70.38 MB"}]}, "scraped_at": "2026-06-09T13:44:14.099Z"}