{"id": "1207658783", "slug": "vr_soccer_96", "title": "VR Soccer '96", "developer": "Gremlin Interactive Ltd.", "publisher": "Interplay", "gog_url": "https://www.gog.com/game/vr_soccer_96", "image": "https://images.gog-statics.com/23cef1bbad35fff715ebc92597047c5678ac262113859f85f48ddd0d2f17d869.webp", "background": "e993bf1253cf03558faf5e55c3c490b6bc0a4981709fc97077ed62bd97544de4", "rating": 3.2, "popularity_ranking": 5461, "release_timestamp": 828223200, "genres": ["Soccer", "Sports", "Team sport"], "tags": ["Classic", "Football", "Good Old Game", "Local Multiplayer", "Management", "Multiplayer", "Multiple Endings", "Soccer", "Sports", "Team sport", "Top-Down"], "is_indev": 0, "is_outdated": 0, "last_update": "2019-06-04T02:31:43.000000Z", "current_version": "1.0", "gog_version": "1.0", "is_new": 0, "is_updated": 0, "is_mod": 0, "is_queued": 0, "is_uploading": 0, "infohash": null, "md5_filename": "vr_soccer_96.md5", "md5_files": [{"hash": "ee38f0cc558104320acd4615098d051b", "filename": "setup_vr_soccer_96_1.0_(28045).exe"}], "magnet_link": null, "gogdb_url": "https://www.gogdb.org/product/1207658783", "pcgamingwiki_url": "https://pcgamingwiki.com/api/gog.php?page=1207658783", "download_links": {"game": {"gofile": {"id": "gofile", "name": "Gofile", "links": [{"label": "game-vr.soccer.96-(28045).rar", "link": "https://gofile.io/d/A0pIia"}]}, "fileditch": {"id": "fileditch", "name": "FileDitch", "links": [{"label": "game-vr.soccer.96-(28045).rar", "link": "https://small.fileditchstuff.me/s13/NcdytiLFvxrbPRjTqfzS.rar"}]}, "pixeldrain": {"id": "pixeldrain", "name": "Pixeldrain", "links": [{"label": "game-vr.soccer.96-(28045).rar", "link": "https://pixeldrain.com/u/SPEvhKbf"}]}, "1fichier": {"id": "1fichier", "name": "1fichier", "links": [{"label": "game-vr.soccer.96-(28045).rar", "link": "https://1fichier.com/?mnvakofgmk4iq49ni2oy"}]}}}, "files": {"game": [{"name": "setup_vr_soccer_96_1.0_(28045).exe", "type": "game", "size": "102.54 MB"}]}, "scraped_at": "2026-06-09T13:39:38.022Z"}