{"id": "1751163083", "slug": "warsaw", "title": "WARSAW", "developer": "Pixelated Milk", "publisher": "Pixelated Milk", "gog_url": "https://www.gog.com/game/warsaw", "image": "https://images.gog-statics.com/ab4e339809ef9e1394e0c6ff1fd9345a42b13938f1fa5239fcd83fca3bbf960b.webp", "background": "2967bdf32e9234b894b360a999d67fd6f32d3f8ddb50e0da6954f350946c201a", "rating": 3.4, "popularity_ranking": 5483, "release_timestamp": 1569963600, "genres": ["Historical", "Role-playing", "Turn-based"], "tags": ["Female Protagonist", "Historical", "Indie", "Military", "Perma Death", "Roguelite", "Role-playing", "Tactical RPG", "Turn-Based"], "is_indev": 0, "is_outdated": 0, "last_update": "2020-03-15T16:53:39.000000Z", "current_version": "111", "gog_version": "111", "is_new": 0, "is_updated": 0, "is_mod": 0, "is_queued": 0, "is_uploading": 0, "infohash": null, "md5_filename": "warsaw.md5", "md5_files": [{"hash": "ccddc26eb4d1679d96f79868d40a9dbc", "filename": "setup_warsaw_111_(36728)-1.bin"}, {"hash": "0fe993f66e692368d4103cd3cab5b2e5", "filename": "setup_warsaw_111_(36728).exe"}], "magnet_link": null, "gogdb_url": "https://www.gogdb.org/product/1751163083", "pcgamingwiki_url": "https://pcgamingwiki.com/api/gog.php?page=1751163083", "download_links": {"game": {"pixeldrain": {"id": "pixeldrain", "name": "Pixeldrain", "links": [{"label": "game-warsaw-(36728).rar", "link": "https://pixeldrain.com/u/5dherWry"}]}, "1fichier": {"id": "1fichier", "name": "1fichier", "links": [{"label": "game-warsaw-(36728).rar", "link": "https://1fichier.com/?a76brewotl3uei7gi6wc"}]}}}, "files": {"game": [{"name": "setup_warsaw_111_(36728).exe", "type": "game", "size": "934.89 KB"}, {"name": "setup_warsaw_111_(36728)-1.bin", "type": "game", "size": "1.72 GB"}]}, "scraped_at": "2026-06-09T13:38:26.729Z"}