{"id": "1800514090", "slug": "withering_rooms", "title": "Withering Rooms", "developer": "Moonless Formless", "publisher": "Perp Games", "gog_url": "https://www.gog.com/game/withering_rooms", "image": "https://images.gog-statics.com/215c1c5929d0bd199888820f7feb18b4569c04ac96a274dd5a8af0c5183fa308.webp", "background": "90a0a372da87b63d9377d68e23640ad875dcf5d074656578d92e6e7a640f4288", "rating": 4.9, "popularity_ranking": 2514, "release_timestamp": 1712264400, "genres": ["Action", "Adventure", "Horror"], "tags": ["2D", "Action", "Adventure", "Female Protagonist", "Horror", "Mystery", "Procedural Generation", "Souls-like", "Stealth"], "is_indev": 0, "is_outdated": 0, "last_update": "2024-05-27T20:00:19.000000Z", "current_version": "v1.25", "gog_version": "v1.25", "is_new": 0, "is_updated": 0, "is_mod": 0, "is_queued": 0, "is_uploading": 0, "infohash": null, "md5_filename": "withering_rooms.md5", "md5_files": [{"hash": "a74749362e88af45a767637ee66dd595", "filename": "setup_withering_rooms_v1.25_(73332)-1.bin"}, {"hash": "b0e5769ff97b1cd171e92a183ec75a89", "filename": "setup_withering_rooms_v1.25_(73332).exe"}], "magnet_link": null, "gogdb_url": "https://www.gogdb.org/product/1800514090", "pcgamingwiki_url": "https://pcgamingwiki.com/api/gog.php?page=1800514090", "download_links": {"game": {"gofile": {"id": "gofile", "name": "Gofile", "links": [{"label": "game-withering.rooms-(73332).rar", "link": "https://gofile.io/d/dkexyq"}]}, "pixeldrain": {"id": "pixeldrain", "name": "Pixeldrain", "links": [{"label": "game-withering.rooms-(73332).rar", "link": "https://pixeldrain.com/u/Wm4ggfv2"}]}, "1fichier": {"id": "1fichier", "name": "1fichier", "links": [{"label": "game-withering.rooms-(73332).rar", "link": "https://1fichier.com/?yynqz889pyplqre08zyl"}]}}}, "files": {"game": [{"name": "setup_withering_rooms_v1.25_(73332).exe", "type": "game", "size": "861.62 KB"}, {"name": "setup_withering_rooms_v1.25_(73332)-1.bin", "type": "game", "size": "2.62 GB"}]}, "scraped_at": "2026-06-09T13:36:40.921Z"}