{"id": "1207659230", "slug": "wizardry_8", "title": "Wizardry 8", "developer": "Sir-Tech Software", "publisher": "Drecom.Co., Ltd.", "gog_url": "https://www.gog.com/game/wizardry_8", "image": "https://images.gog-statics.com/e4022bb6089e97082e99612ffa1dc0c407344a2d899eb6ed524565e650384939.webp", "background": "8c2375e834a81802ecebef511dacb288c5169d1cf339035d52b29a5514a211d6", "rating": 4.7, "popularity_ranking": 1707, "release_timestamp": 1005775200, "genres": ["Fantasy", "Role-playing", "Turn-based"], "tags": ["Atmospheric", "CRPG", "Classic", "Dungeon Crawler", "Exploration", "Fantasy", "First-Person", "Role-playing", "Science", "Turn-Based"], "is_indev": 0, "is_outdated": 0, "last_update": null, "current_version": "2001_12_23", "gog_version": "2001_12_23", "is_new": 0, "is_updated": 0, "is_mod": 0, "is_queued": 0, "is_uploading": 0, "infohash": null, "md5_filename": "wizardry_8.md5", "md5_files": [{"hash": "8048bbe9d2edab21a275aac4bee22dca", "filename": "setup_wizardry_8_2001_12_23_(22306).exe"}, {"hash": "754bb3d3d4f625252e95f3640661bd21", "filename": "wizardry_8_avatar.zip"}, {"hash": "05d382a17f8248f6d0b5cbb1ef18e372", "filename": "wizardry_8_manuals.zip"}, {"hash": "f0348298026b4b4850093836a12f5a18", "filename": "wizardry_8_ost_flac.zip"}, {"hash": "bda836c0563bc8e88ecdcf755b547221", "filename": "wizardry_8_soundtrack.zip"}, {"hash": "7b8f921e3ff25dec776a6a98b5a878da", "filename": "wizardry_8_wallpaper.zip"}], "magnet_link": null, "gogdb_url": "https://www.gogdb.org/product/1207659230", "pcgamingwiki_url": "https://pcgamingwiki.com/api/gog.php?page=1207659230", "download_links": {"goodie": {"gofile": {"id": "gofile", "name": "Gofile", "links": [{"label": "extras-wizardry.8.rar", "link": "https://gofile.io/d/u3Bv95"}]}, "fileditch": {"id": "fileditch", "name": "FileDitch", "links": [{"label": "extras-wizardry.8.rar", "link": "https://small.fileditchstuff.me/s16/YQcThNuvFFQYSstOGrnS.rar"}]}, "pixeldrain": {"id": "pixeldrain", "name": "Pixeldrain", "links": [{"label": "extras-wizardry.8.rar", "link": "https://pixeldrain.com/u/kjM9nzm4"}]}, "1fichier": {"id": "1fichier", "name": "1fichier", "links": [{"label": "extras-wizardry.8.rar", "link": "https://1fichier.com/?vhh1vzlbv8v2rdqudjhu"}]}}, "game": {"gofile": {"id": "gofile", "name": "Gofile", "links": [{"label": "game-wizardry.8-(22306).rar", "link": "https://gofile.io/d/TfyKmp"}]}, "pixeldrain": {"id": "pixeldrain", "name": "Pixeldrain", "links": [{"label": "game-wizardry.8-(22306).rar", "link": "https://pixeldrain.com/u/8TqMrMsx"}]}, "1fichier": {"id": "1fichier", "name": "1fichier", "links": [{"label": "game-wizardry.8-(22306).rar", "link": "https://1fichier.com/?g9izsuxqb6t4u8hgbqkc"}]}}}, "files": {"game": [{"name": "setup_wizardry_8_2001_12_23_(22306).exe", "type": "game", "size": "1.32 GB"}], "goodie": [{"name": "wizardry_8_avatar.zip", "type": "goodie", "size": "51.87 KB"}, {"name": "wizardry_8_manuals.zip", "type": "goodie", "size": "67.92 MB"}, {"name": "wizardry_8_ost_flac.zip", "type": "goodie", "size": "127.18 MB"}, {"name": "wizardry_8_soundtrack.zip", "type": "goodie", "size": "39.03 MB"}, {"name": "wizardry_8_wallpaper.zip", "type": "goodie", "size": "5.59 MB"}]}, "scraped_at": "2026-06-09T13:36:34.050Z"}